rotational_placement/__init__.py
rotational_placement/_rp_ff.py
rotational_placement/_rp_num.py
rotational_placement/_rp_sym.py
rotational_placement/config.json
rotational_placement/experiment_class.py
rotational_placement/load_config.py
rotational_placement/make_data_dir.py
rotational_placement/make_plot_dir.py
rotational_placement/plot_density.py
rotational_placement/plot_flower.py
rotational_placement-0.1.7.dist-info/METADATA
rotational_placement-0.1.7.dist-info/WHEEL
rotational_placement-0.1.7.dist-info/licenses/LICENSE
rotational_placement-0.1.7.dist-info/RECORD
