Metadata-Version: 2.3
Name: rotational_placement
Version: 0.1.7
Summary: A package for generating and visualizing data related to the concept of rotational placement
Project-URL: Homepage, https://github.com/Ingwehr/RotationalPlacementPackage
Author-email: ingwehr <backlund.hugo@gmail.com>
License: Academic Free License (AFL)
License-File: LICENSE
Classifier: License :: OSI Approved :: Academic Free License (AFL)
Classifier: Operating System :: OS Independent
Classifier: Programming Language :: Python :: 3
Classifier: Programming Language :: Python :: 3.12
Requires-Python: >=3.12
Requires-Dist: matplotlib
Requires-Dist: numpy
Requires-Dist: sympy
